kot_cloud_telegram
