Metadata-Version: 2.1
Name: kot-cloud-telegram
Version: 0.5.1
Summary: Hot reload, remote controlled and expandable telegram bot.
Home-page: https://github.com/KOT-database/KOT-Cloud-Telegram
License: MIT
Platform: UNKNOWN
Requires-Python: >= 3
